ngram_lm-0.1.0.dist-info/METADATA
ngram_lm-0.1.0.dist-info/top_level.txt
ngram_lm-0.1.0.dist-info/WHEEL
ngram_lm-0.1.0.dist-info/RECORD
ngram_lm.libs/libngram_lm-6e6d60be.so
ngram_lm/trie.pypy37-pp73-x86_64-linux-gnu.so
ngram_lm/word.pypy37-pp73-x86_64-linux-gnu.so
