Metadata-Version: 2.1
Name: ngram-lm
Version: 0.1.0
Summary: UNKNOWN
Home-page: UNKNOWN
Author: João Fé
Author-email: joaofe2000@gmail.com
License: UNKNOWN
Platform: UNKNOWN
